odoo_xmlrpc_wrapper/__init__.py
odoo_xmlrpc_wrapper/odoo_xmlrpc_wrapper.py
odoo_xmlrpc_wrapper-1.1.1.dist-info/LICENSE
odoo_xmlrpc_wrapper-1.1.1.dist-info/METADATA
odoo_xmlrpc_wrapper-1.1.1.dist-info/WHEEL
odoo_xmlrpc_wrapper-1.1.1.dist-info/top_level.txt
odoo_xmlrpc_wrapper-1.1.1.dist-info/RECORD
