Metadata-Version: 2.1
Name: odoo_xmlrpc_wrapper
Version: 1.1.1
Summary: A simple Python library to make CRUD process easier
Home-page: https://github.com/cagatayuresin/odoo-xmlrpc-wrapper
Author: Cagatay URESIN
Author-email: Cagatay URESIN <cagatayuresin@gmail.com>
Maintainer-email: Cagatay URESIN <cagatayuresin@gmail.com>
License: MIT License
Project-URL: Homepage, https://github.com/cagatayuresin/odoo-xmlrpc-wrapper
Project-URL: Bug Reports, https://github.com/cagatayuresin/odoo-xmlrpc-wrapper/issues
Project-URL: Buy Me A Coffee, https://www.buymeacoffee.com/cagatayuresin
Project-URL: Source, https://github.com/cagatayuresin/odoo-xmlrpc-wrapper
Keywords: odoo,external,api,xmlrpc,rpc,wrapper
Classifier: Development Status :: 5 - Production/Stable
Classifier: Environment :: Console
Classifier: Framework :: Odoo
Classifier: Framework :: Odoo :: 16.0
Classifier: Intended Audience :: Developers
Classifier: Intended Audience :: System Administrators
Classifier: License :: Freeware
Classifier: License :: OSI Approved :: MIT License
Classifier: Operating System :: OS Independent
Classifier: Programming Language :: Python :: 3 :: Only
Classifier: Programming Language :: Python :: 3.7
Classifier: Topic :: Office/Business
Classifier: Topic :: Software Development :: Libraries
Classifier: Topic :: Software Development :: Libraries :: Python Modules
Requires-Python: >=3.7
License-File: LICENSE
